kwja/__init__.py
kwja/__main__.py
kwja/callbacks/__init__.py
kwja/callbacks/base_module_writer.py
kwja/callbacks/char_module_writer.py
kwja/callbacks/seq2seq_module_writer.py
kwja/callbacks/typo_module_writer.py
kwja/callbacks/utils.py
kwja/callbacks/word_module_writer.py
kwja/cli/__init__.py
kwja/cli/cli.py
kwja/cli/config.py
kwja/cli/utils.py
kwja/datamodule/datamodule.py
kwja/datamodule/datasets/__init__.py
kwja/datamodule/datasets/base.py
kwja/datamodule/datasets/char.py
kwja/datamodule/datasets/char_inference.py
kwja/datamodule/datasets/seq2seq.py
kwja/datamodule/datasets/seq2seq_inference.py
kwja/datamodule/datasets/typo.py
kwja/datamodule/datasets/typo_inference.py
kwja/datamodule/datasets/utils.py
kwja/datamodule/datasets/word.py
kwja/datamodule/datasets/word_inference.py
kwja/datamodule/examples/__init__.py
kwja/datamodule/examples/char.py
kwja/datamodule/examples/seq2seq.py
kwja/datamodule/examples/typo.py
kwja/datamodule/examples/word.py
kwja/modules/__init__.py
kwja/modules/base.py
kwja/modules/char.py
kwja/modules/components/crf.py
kwja/modules/components/deberta_v2.py
kwja/modules/components/head.py
kwja/modules/components/logits_processor.py
kwja/modules/components/pooling.py
kwja/modules/functions/__init__.py
kwja/modules/functions/loss.py
kwja/modules/seq2seq.py
kwja/modules/typo.py
kwja/modules/word.py
kwja/py.typed
kwja/resource/jumandic/grammar.json
kwja/resource/jumandic/jumandic.db
kwja/resource/jumandic/jumandic_canon.db
kwja/resource/reading_prediction/freq_all.txt
kwja/resource/reading_prediction/kanjidic
kwja/resource/reading_prediction/vocab.txt
kwja/resource/typo_correction/multi_char_vocab.txt
kwja/utils/__init__.py
kwja/utils/cohesion_analysis.py
kwja/utils/constants.py
kwja/utils/dependency_parsing.py
kwja/utils/jumandic.py
kwja/utils/kanjidic.py
kwja/utils/logging_util.py
kwja/utils/normalization.py
kwja/utils/reader.py
kwja/utils/reading_prediction.py
kwja/utils/seq2seq_format.py
kwja/utils/sub_document.py
kwja-2.5.1.dist-info/LICENSE
kwja-2.5.1.dist-info/METADATA
kwja-2.5.1.dist-info/WHEEL
kwja-2.5.1.dist-info/entry_points.txt
kwja-2.5.1.dist-info/RECORD
