Metadata-Version: 2.3
Name: kwja
Version: 2.5.1
Summary: A unified Japanese analyzer based on foundation models
License: MIT
Keywords: NLP,Japanese
Author: Hirokazu Kiyomaru
Author-email: kiyomaru@i.kyoto-u.ac.jp
Maintainer: Hirokazu Kiyomaru
Maintainer-email: kiyomaru@i.kyoto-u.ac.jp
Requires-Python: >=3.9,<3.14
Classifier: License :: OSI Approved :: MIT License
Classifier: Natural Language :: Japanese
Classifier: Environment :: GPU
Classifier: Environment :: Console
Classifier: Operating System :: MacOS :: MacOS X
Classifier: Operating System :: Microsoft :: Windows
Classifier: Operating System :: POSIX :: Linux
Classifier: Programming Language :: Python :: 3
Classifier: Programming Language :: Python :: 3.9
Classifier: Programming Language :: Python :: 3.10
Classifier: Programming Language :: Python :: 3.11
Classifier: Programming Language :: Python :: 3.12
Classifier: Programming Language :: Python :: 3.13
Classifier: Topic :: Scientific/Engineering
Classifier: Topic :: Text Processing
Requires-Dist: cohesion-tools (>=0.7.5,<0.8.0)
Requires-Dist: hydra-core (>=1.2)
Requires-Dist: jinf (>=1.0.4)
Requires-Dist: lightning (>=2.5.0,<2.6.0)
Requires-Dist: numpy (>=2.0)
Requires-Dist: omegaconf (>=2.1)
Requires-Dist: pure-cdb (>=4.0)
Requires-Dist: pyyaml (>=6.0)
Requires-Dist: regex (>=2024.7.24)
Requires-Dist: rhoknp (>=1.6)
Requires-Dist: rich (>=14.0.0,<15.0.0)
Requires-Dist: tokenizers (>=0.21.4,<0.22.0)
Requires-Dist: torch (>=2.4.0,<2.8.0)
Requires-Dist: transformers[sentencepiece] (>=4.50.3,<4.51.0)
Requires-Dist: typer-slim (>=0.15.0,<0.16.0)
Requires-Dist: typing-extensions (>=4.0) ; python_version < "3.10"
Project-URL: Changelog, https://github.com/ku-nlp/kwja/blob/main/CHANGELOG.md
Project-URL: Homepage, https://github.com/ku-nlp/kwja
Project-URL: Issues, https://github.com/ku-nlp/kwja/issues
Project-URL: Repository, https://github.com/ku-nlp/kwja
